Metadata-Version: 2.1
Name: kaniattrdict
Version: 3.0.2
Summary: A dict with attribute-style access
Home-page: 
Author: Fx Kirin
Author-email: fx.kirin@gmail.com
License: MIT License
Classifier: Development Status :: 7 - Inactive
Classifier: Intended Audience :: Developers
Classifier: License :: OSI Approved :: MIT License
Classifier: Programming Language :: Python :: 2
Classifier: Programming Language :: Python :: 2.7
Classifier: Programming Language :: Python :: 3
Classifier: Programming Language :: Python :: Implementation :: CPython
Classifier: Programming Language :: Python :: Implementation :: PyPy
